nonebot_plugin_finallines-0.1.1.post2.dist-info/METADATA
nonebot_plugin_finallines-0.1.1.post2.dist-info/WHEEL
nonebot_plugin_finallines-0.1.1.post2.dist-info/licenses/LICENSE
nonebot_plugin_finallines/__init__.py
nonebot_plugin_finallines/final_lines.json
nonebot_plugin_finallines-0.1.1.post2.dist-info/RECORD
