Metadata-Version: 2.1
Name: nonebot-plugin-finallines
Version: 0.1.1.post2
Summary: A NoneBot plugin for random final lines.
Keywords: nonebot nonebot2 bot qq final lines
Home-page: https://github.com/Perseus037/nonebot_plugin_finallines/
Author-Email: Perseus037 <1209228678@qq.com>
License: MIT
Classifier: Natural Language :: Chinese (Simplified)
Classifier: Topic :: Communications
Classifier: Topic :: Communications :: Chat
Classifier: Topic :: Internet
Classifier: Topic :: Internet :: WWW/HTTP
Classifier: Topic :: Internet :: WWW/HTTP :: Dynamic Content
Project-URL: Homepage, https://github.com/Perseus037/nonebot_plugin_finallines/
Requires-Python: <4.0,>=3.8
Requires-Dist: nonebot2>=2.1.1
Requires-Dist: pydantic<2,>=1.10.13
Requires-Dist: nonebot-adapter-onebot>=2.3.1
Requires-Dist: nonebot-plugin-userinfo>=0.1.3
Requires-Dist: nonebot-plugin-send-anything-anywhere>=0.4.0
